<?xml version="1.0" encoding="UTF-8"?>
<objects serializationModel="Studio.02.01.00">
	<object class="AudioFile" id="{1fd3e900-d305-47ad-a76a-7e0f71ec85f7}">
		<property name="assetPath">
			<value>SeeTheMoon.mp3</value>
		</property>
		<property name="isStreaming">
			<value>true</value>
		</property>
		<property name="frequencyInKHz">
			<value>44.0999985</value>
		</property>
		<property name="channelCount">
			<value>2</value>
		</property>
		<property name="length">
			<value>233.66530612244898</value>
		</property>
		<relationship name="masterAssetFolder">
			<destination>{71e9a827-6a20-4e8d-81b3-2365386d4f15}</destination>
		</relationship>
	</object>
</objects>
